{
  "schemaVersion": 1,
  "kind": "P02_DATABASE_INTEGRATION",
  "runId": "a6fe0084-78f0-4733-991b-b154d56063dc",
  "generatedAt": "2026-07-12T20:28:27.152Z",
  "sourceSha": "59ce65c0c50c3875ea17c34cf200ca048700c70c",
  "nodeVersion": "v24.18.0",
  "platform": "linux/x64",
  "status": "PASS",
  "skipped": 0,
  "checks": {
    "provider": {
      "dockerPlatform": "linux/amd64",
      "runnerOs": "linux",
      "runnerArch": "x64",
      "image": "postgres:17.10-bookworm",
      "immutableReference": "postgres:17.10-bookworm@sha256:9cc09bb9a1b9da469658a6fab7bbced9ece6ca99174e1b93c1c4cc1a12f741cf",
      "digest": "sha256:9cc09bb9a1b9da469658a6fab7bbced9ece6ca99174e1b93c1c4cc1a12f741cf",
      "inspectedOs": "linux",
      "inspectedArch": "amd64",
      "repoDigests": [
        "postgres@sha256:9cc09bb9a1b9da469658a6fab7bbced9ece6ca99174e1b93c1c4cc1a12f741cf"
      ],
      "containerId": "3f950122a3e2d3e56d0ce98561bc101a1ebe251fc8234a798ffc1af1f85c166d",
      "serverVersion": "17.10 (Debian 17.10-1.pgdg12+1)",
      "serverMajor": 17,
      "lcCollate": "en_US.utf8",
      "lcCtype": "en_US.utf8",
      "timezone": "Etc/UTC",
      "ssl": "off"
    },
    "migrations": {
      "first": true,
      "repeat": true,
      "existingSchema": {
        "independentDatabase": true,
        "prepared": true,
        "preserved": true,
        "completedMigrations": 2,
        "beforeCatalog": {
          "payload": {
            "tables": [
              "_prisma_migrations",
              "p02_preexisting_catalog"
            ]
          },
          "sha256": "9c770abd6b242f5d6f8fe7eec596e0f940aa3dc5214af6bdddd23bc53ce8dc24"
        },
        "afterCatalog": {
          "payload": {
            "tables": [
              "_prisma_migrations",
              "agents",
              "p02_preexisting_catalog",
              "tenants"
            ]
          },
          "sha256": "1b35b00c013a4970a5d706765dd716e3fe3488783ac960fbe57b0a3528a9672c"
        },
        "migrationHistory": [
          {
            "migrationName": "20260710000000_existing_catalog_baseline",
            "checksum": "07df3c3d18d5825b4ff89edee462bb160422f5132624df82bdca8800e582431e",
            "finished": true,
            "rolledBack": false
          },
          {
            "migrationName": "20260711000000_init_prisma_rls_scaffold",
            "checksum": "129f3ce0dd1164f30c1ea185b956989198457f6a2b10954a5eb9c160f5c31aca",
            "finished": true,
            "rolledBack": false
          }
        ]
      },
      "rollback": {
        "failed": true,
        "partialTableAbsent": true,
        "rolledBackRows": 1,
        "repaired": true
      },
      "concurrent": {
        "safe": true,
        "exitCodes": [
          0,
          0
        ],
        "completedRows": 1
      }
    },
    "rls": [
      {
        "relrowsecurity": true,
        "relforcerowsecurity": true,
        "table_owner": "p02_admin",
        "policyname": "agents_tenant_isolation",
        "qual": "(tenant_id = (current_setting('app.tenant_id'::text))::uuid)",
        "with_check": "(tenant_id = (current_setting('app.tenant_id'::text))::uuid)"
      }
    ],
    "roles": [
      {
        "rolname": "p02_admin",
        "rolsuper": true,
        "rolbypassrls": true
      },
      {
        "rolname": "p02_app",
        "rolsuper": false,
        "rolbypassrls": false
      }
    ],
    "seed": [
      {
        "tenant_id": "10000000-0000-4000-8000-000000000001",
        "logical_id": "main",
        "id": "a0000000-0000-4000-8000-000000000001"
      },
      {
        "tenant_id": "20000000-0000-4000-8000-000000000002",
        "logical_id": "main",
        "id": "b0000000-0000-4000-8000-000000000002"
      }
    ],
    "checksPassed": 27,
    "checksTotal": 27,
    "testResults": {
      "passed": 27,
      "failed": 0,
      "skipped": 0,
      "todo": 0,
      "total": 27
    },
    "testOutputSha256": "c34d385df95b1422b90d4b173badaf1a43143764a6ccf1672cc26348a34d63c5"
  },
  "cleanup": {
    "attempted": true,
    "containerId": "3f950122a3e2d3e56d0ce98561bc101a1ebe251fc8234a798ffc1af1f85c166d",
    "removed": true
  }
}
